alpaca_mcp_server/__init__.py
alpaca_mcp_server/cli.py
alpaca_mcp_server/config.py
alpaca_mcp_server/helpers.py
alpaca_mcp_server/server.py
alpaca_mcp_server-1.0.10.dist-info/METADATA
alpaca_mcp_server-1.0.10.dist-info/WHEEL
alpaca_mcp_server-1.0.10.dist-info/entry_points.txt
alpaca_mcp_server-1.0.10.dist-info/licenses/LICENSE
alpaca_mcp_server-1.0.10.dist-info/RECORD
