Metadata-Version: 2.4
Name: alpaca-mcp-server
Version: 1.0.10
Summary: Alpaca Trading API integration for Model Context Protocol (MCP)
Project-URL: Homepage, https://alpaca.markets/
Project-URL: Repository, https://github.com/alpacahq/alpaca-mcp-server
Project-URL: Bug Tracker, https://github.com/alpacahq/alpaca-mcp-server/issues
Project-URL: Documentation, https://github.com/alpacahq/alpaca-mcp-server#readme
Author-email: Alpaca <info@alpaca.markets>
License: MIT
License-File: LICENSE
Keywords: ai,alpaca,finance,llm,mcp,model-context-protocol,trading
Classifier: Development Status :: 4 - Beta
Classifier: Intended Audience :: Developers
Classifier: License :: OSI Approved :: MIT License
Classifier: Programming Language :: Python :: 3
Classifier: Programming Language :: Python :: 3.10
Classifier: Programming Language :: Python :: 3.11
Classifier: Programming Language :: Python :: 3.12
Classifier: Topic :: Office/Business :: Financial :: Investment
Classifier: Topic :: Scientific/Engineering :: Artificial Intelligence
Classifier: Topic :: Software Development :: Libraries :: Python Modules
Requires-Python: >=3.10
Requires-Dist: alpaca-py>=0.29.0
Requires-Dist: click>=8.1.0
Requires-Dist: mcp<1.25.0,>=1.21.0
Requires-Dist: python-dotenv>=1.0.0
Provides-Extra: dev
Requires-Dist: mypy>=1.0.0; extra == 'dev'
Requires-Dist: pytest-asyncio>=0.23.0; extra == 'dev'
Requires-Dist: pytest>=7.0.0; extra == 'dev'
Requires-Dist: ruff>=0.1.0; extra == 'dev'
